cchdo/uow/__init__.py
cchdo/uow/__main__.py
cchdo/uow/bootstrap.py
cchdo/uow/commit.py
cchdo/uow/console.py
cchdo/uow/fetch.py
cchdo/uow/info.py
cchdo/uow/init.py
cchdo/uow/list.py
cchdo/uow/refresh.py
cchdo/uow/status.py
cchdo/uow/uow_json.py
cchdo.uow-1.5.0.dist-info/LICENSE.md
cchdo.uow-1.5.0.dist-info/METADATA
cchdo.uow-1.5.0.dist-info/WHEEL
cchdo.uow-1.5.0.dist-info/entry_points.txt
cchdo.uow-1.5.0.dist-info/top_level.txt
cchdo.uow-1.5.0.dist-info/RECORD
